LICENSE
MANIFEST.in
README.rst
setup.cfg
setup.py
construct_legacy/__init__.py
construct_legacy/adapters.py
construct_legacy/core.py
construct_legacy/debug.py
construct_legacy/macros.py
construct_legacy/version.py
construct_legacy.egg-info/PKG-INFO
construct_legacy.egg-info/SOURCES.txt
construct_legacy.egg-info/dependency_links.txt
construct_legacy.egg-info/requires.txt
construct_legacy.egg-info/top_level.txt
construct_legacy/formats/__init__.py
construct_legacy/formats/data/__init__.py
construct_legacy/formats/data/cap.py
construct_legacy/formats/data/snoop.py
construct_legacy/formats/executable/__init__.py
construct_legacy/formats/executable/elf32.py
construct_legacy/formats/executable/pe32.py
construct_legacy/formats/filesystem/__init__.py
construct_legacy/formats/filesystem/ext2.py
construct_legacy/formats/filesystem/fat16.py
construct_legacy/formats/filesystem/mbr.py
construct_legacy/formats/graphics/__init__.py
construct_legacy/formats/graphics/bmp.py
construct_legacy/formats/graphics/emf.py
construct_legacy/formats/graphics/gif.py
construct_legacy/formats/graphics/png.py
construct_legacy/formats/graphics/wmf.py
construct_legacy/lib/__init__.py
construct_legacy/lib/binary.py
construct_legacy/lib/bitstream.py
construct_legacy/lib/container.py
construct_legacy/lib/expr.py
construct_legacy/lib/hex.py
construct_legacy/lib/py3compat.py
construct_legacy/protocols/__init__.py
construct_legacy/protocols/ipstack.py
construct_legacy/protocols/application/__init__.py
construct_legacy/protocols/application/dns.py
construct_legacy/protocols/layer2/__init__.py
construct_legacy/protocols/layer2/arp.py
construct_legacy/protocols/layer2/ethernet.py
construct_legacy/protocols/layer2/mtp2.py
construct_legacy/protocols/layer3/__init__.py
construct_legacy/protocols/layer3/dhcpv4.py
construct_legacy/protocols/layer3/dhcpv6.py
construct_legacy/protocols/layer3/icmpv4.py
construct_legacy/protocols/layer3/igmpv2.py
construct_legacy/protocols/layer3/ipv4.py
construct_legacy/protocols/layer3/ipv6.py
construct_legacy/protocols/layer3/mtp3.py
construct_legacy/protocols/layer4/__init__.py
construct_legacy/protocols/layer4/isup.py
construct_legacy/protocols/layer4/tcp.py
